homepilot/__init__.py
homepilot/actuator.py
homepilot/api.py
homepilot/const.py
homepilot/cover.py
homepilot/device.py
homepilot/hub.py
homepilot/light.py
homepilot/manager.py
homepilot/scenes.py
homepilot/sensor.py
homepilot/switch.py
homepilot/thermostat.py
homepilot/wallcontroller.py
pyrademacher-0.15.0.dist-info/licenses/LICENSE
tests/__init__.py
tests/test_api.py
tests/test_auto_config_device.py
tests/test_cover.py
tests/test_hub.py
tests/test_manager.py
tests/test_scenes.py
tests/test_sensor.py
tests/test_switch.py
tests/test_thermostat.py
pyrademacher-0.15.0.dist-info/METADATA
pyrademacher-0.15.0.dist-info/WHEEL
pyrademacher-0.15.0.dist-info/top_level.txt
pyrademacher-0.15.0.dist-info/RECORD
