Metadata-Version: 2.4
Name: pyrademacher
Version: 0.15.0
Summary: Control devices connected to your Rademacher Homepilot (or Start2Smart) hub
Home-page: https://github.com/peribeir/pyrademacher
Author: Pedro Ribeiro
Author-email: pedroeusebio@gmail.com
Project-URL: Bug Tracker, https://github.com/peribeir/pyrademacher/issues
Classifier: Development Status :: 4 - Beta
Classifier: Intended Audience :: Developers
Classifier: Programming Language :: Python :: 3.10
Classifier: Programming Language :: Python :: 3.11
Classifier: Programming Language :: Python :: 3.12
Classifier: License :: OSI Approved :: GNU General Public License v3 (GPLv3)
Classifier: Operating System :: OS Independent
Requires-Python: >=3.10
License-File: LICENSE
Requires-Dist: aiohttp>=3.8.1
Dynamic: author
Dynamic: author-email
Dynamic: classifier
Dynamic: description
Dynamic: description-content-type
Dynamic: home-page
Dynamic: license-file
Dynamic: project-url
Dynamic: requires-dist
Dynamic: requires-python
Dynamic: summary
